<annotation>
    <folder>images</folder>
    <filename>ckau0b1gty7b20781qvvighwt.jpeg</filename>
    <path>/Users/weishungchung/Desktop/exports1/images/ckau0b1gty7b20781qvvighwt.jpeg</path>
    <source>
        <database>Unknown</database>
    </source>
    <size>
        <width>640</width>
        <height>480</height>
        <depth>3</depth>
    </size>
    <segmented>0</segmented>
    <object>
        <name>smoke</name>
        <pose>Unspecified</pose>
        <truncated>0</truncated>
        <difficult>0</difficult>
        <bndbox>
                <xmin>365.0</xmin>
                <ymin>191.0</ymin>
                <xmax>372.0</xmax>
                <ymax>194.0</ymax>
            </bndbox>
        </object>
    <object>
        <name>smoke</name>
        <pose>Unspecified</pose>
        <truncated>0</truncated>
        <difficult>0</difficult>
        <bndbox>
                <xmin>251.0</xmin>
                <ymin>192.0</ymin>
                <xmax>263.0</xmax>
                <ymax>193.0</ymax>
            </bndbox>
        </object>
    </annotation>