<annotation>
    <folder>images</folder>
    <filename>ckau0culky71d07559q9dtd0n.jpeg</filename>
    <path>/Users/weishungchung/Desktop/exports1/images/ckau0culky71d07559q9dtd0n.jpeg</path>
    <source>
        <database>Unknown</database>
    </source>
    <size>
        <width>640</width>
        <height>480</height>
        <depth>3</depth>
    </size>
    <segmented>0</segmented>
    <object>
        <name>smoke</name>
        <pose>Unspecified</pose>
        <truncated>0</truncated>
        <difficult>0</difficult>
        <bndbox>
                <xmin>366.0</xmin>
                <ymin>185.0</ymin>
                <xmax>383.0</xmax>
                <ymax>194.0</ymax>
            </bndbox>
        </object>
    </annotation>